[{"fields": {"model": "placeholder", "app_label": "cms"}, "model": "contenttypes.contenttype", "pk": 1}, {"fields": {"model": "page", "app_label": "cms"}, "model": "contenttypes.contenttype", "pk": 2}, {"fields": {"model": "logentry", "app_label": "admin"}, "model": "contenttypes.contenttype", "pk": 3}, {"fields": {"model": "permission", "app_label": "auth"}, "model": "contenttypes.contenttype", "pk": 4}, {"fields": {"model": "group", "app_label": "auth"}, "model": "contenttypes.contenttype", "pk": 5}, {"fields": {"model": "user", "app_label": "auth"}, "model": "contenttypes.contenttype", "pk": 6}, {"fields": {"model": "contenttype", "app_label": "contenttypes"}, "model": "contenttypes.contenttype", "pk": 7}, {"fields": {"model": "session", "app_label": "sessions"}, "model": "contenttypes.contenttype", "pk": 8}, {"fields": {"model": "departamentoacademico", "app_label": "desenvolvimento"}, "model": "contenttypes.contenttype", "pk": 9}, {"fields": {"model": "professor", "app_label": "desenvolvimento"}, "model": "contenttypes.contenttype", "pk": 10}, {"fields": {"model": "dadosdeprofessor", "app_label": "desenvolvimento"}, "model": "contenttypes.contenttype", "pk": 11}, {"fields": {"model": "formacao", "app_label": "desenvolvimento"}, "model": "contenttypes.contenttype", "pk": 12}, {"fields": {"model": "areadeatuacao", "app_label": "desenvolvimento"}, "model": "contenttypes.contenttype", "pk": 13}, {"fields": {"model": "curso", "app_label": "desenvolvimento"}, "model": "contenttypes.contenttype", "pk": 14}, {"fields": {"model": "matriz", "app_label": "desenvolvimento"}, "model": "contenttypes.contenttype", "pk": 15}, {"fields": {"model": "disciplina", "app_label": "desenvolvimento"}, "model": "contenttypes.contenttype", "pk": 16}, {"fields": {"model": "relacaodisciplinacurso", "app_label": "desenvolvimento"}, "model": "contenttypes.contenttype", "pk": 17}, {"fields": {"model": "coordenacao", "app_label": "desenvolvimento"}, "model": "contenttypes.contenttype", "pk": 18}, {"fields": {"model": "integrante", "app_label": "desenvolvimento"}, "model": "contenttypes.contenttype", "pk": 19}, {"fields": {"model": "integranteprofessor", "app_label": "desenvolvimento"}, "model": "contenttypes.contenttype", "pk": 20}, {"fields": {"model": "artigo", "app_label": "desenvolvimento"}, "model": "contenttypes.contenttype", "pk": 21}, {"fields": {"model": "artigoemperiodico", "app_label": "desenvolvimento"}, "model": "contenttypes.contenttype", "pk": 22}, {"fields": {"model": "artigoemconferencia", "app_label": "desenvolvimento"}, "model": "contenttypes.contenttype", "pk": 23}, {"fields": {"model": "projeto", "app_label": "desenvolvimento"}, "model": "contenttypes.contenttype", "pk": 24}, {"fields": {"model": "evento", "app_label": "desenvolvimento"}, "model": "contenttypes.contenttype", "pk": 25}, {"fields": {"model": "planodeaula", "app_label": "desenvolvimento"}, "model": "contenttypes.contenttype", "pk": 26}, {"fields": {"model": "site", "app_label": "sites"}, "model": "contenttypes.contenttype", "pk": 27}, {"fields": {"model": "usersettings", "app_label": "cms"}, "model": "contenttypes.contenttype", "pk": 28}, {"fields": {"model": "globalpagepermission", "app_label": "cms"}, "model": "contenttypes.contenttype", "pk": 29}, {"fields": {"model": "pagepermission", "app_label": "cms"}, "model": "contenttypes.contenttype", "pk": 30}, {"fields": {"model": "pageuser", "app_label": "cms"}, "model": "contenttypes.contenttype", "pk": 31}, {"fields": {"model": "pageusergroup", "app_label": "cms"}, "model": "contenttypes.contenttype", "pk": 32}, {"fields": {"model": "cmsplugin", "app_label": "cms"}, "model": "contenttypes.contenttype", "pk": 33}, {"fields": {"model": "title", "app_label": "cms"}, "model": "contenttypes.contenttype", "pk": 34}, {"fields": {"model": "placeholderreference", "app_label": "cms"}, "model": "contenttypes.contenttype", "pk": 35}, {"fields": {"model": "staticplaceholder", "app_label": "cms"}, "model": "contenttypes.contenttype", "pk": 36}, {"fields": {"model": "aliaspluginmodel", "app_label": "cms"}, "model": "contenttypes.contenttype", "pk": 37}, {"fields": {"model": "urlconfrevision", "app_label": "cms"}, "model": "contenttypes.contenttype", "pk": 38}, {"fields": {"model": "cachekey", "app_label": "menus"}, "model": "contenttypes.contenttype", "pk": 39}, {"fields": {"model": "diadasemana", "app_label": "desenvolvimento"}, "model": "contenttypes.contenttype", "pk": 40}, {"fields": {"model": "horariodaaula", "app_label": "desenvolvimento"}, "model": "contenttypes.contenttype", "pk": 41}, {"fields": {"model": "relacaodiadasemanahorariodeaula", "app_label": "desenvolvimento"}, "model": "contenttypes.contenttype", "pk": 42}, {"fields": {"model": "oferecimento", "app_label": "desenvolvimento"}, "model": "contenttypes.contenttype", "pk": 43}, {"fields": {"model": "comissao", "app_label": "desenvolvimento"}, "model": "contenttypes.contenttype", "pk": 44}, {"fields": {"model": "colegiado", "app_label": "desenvolvimento"}, "model": "contenttypes.contenttype", "pk": 45}, {"fields": {"model": "aluno", "app_label": "desenvolvimento"}, "model": "contenttypes.contenttype", "pk": 46}, {"fields": {"model": "membroeleito", "app_label": "desenvolvimento"}, "model": "contenttypes.contenttype", "pk": 47}, {"fields": {"model": "nde", "app_label": "desenvolvimento"}, "model": "contenttypes.contenttype", "pk": 48}, {"fields": {"model": "empresajunior", "app_label": "desenvolvimento"}, "model": "contenttypes.contenttype", "pk": 49}, {"fields": {"model": "centroacademico", "app_label": "desenvolvimento"}, "model": "contenttypes.contenttype", "pk": 50}, {"fields": {"model": "estagiario", "app_label": "desenvolvimento"}, "model": "contenttypes.contenttype", "pk": 51}, {"fields": {"model": "calendarioacademico", "app_label": "desenvolvimento"}, "model": "contenttypes.contenttype", "pk": 52}, {"fields": {"model": "pessoa", "app_label": "desenvolvimento"}, "model": "contenttypes.contenttype", "pk": 55}, {"fields": {"model": "servidor", "app_label": "desenvolvimento"}, "model": "contenttypes.contenttype", "pk": 56}, {"fields": {"model": "tecnicoadm", "app_label": "desenvolvimento"}, "model": "contenttypes.contenttype", "pk": 57}, {"fields": {"model": "chefiadodepartamento", "app_label": "desenvolvimento"}, "model": "contenttypes.contenttype", "pk": 58}, {"fields": {"model": "infraestrutura", "app_label": "desenvolvimento"}, "model": "contenttypes.contenttype", "pk": 59}, {"fields": {"model": "sala", "app_label": "desenvolvimento"}, "model": "contenttypes.contenttype", "pk": 60}, {"fields": {"expire_date": "2016-06-06T15:04:57.951Z", "session_data": "ZTQ2ZjRkMDc3YzliZGQ5YzY4NjNhODA5MWY2ZGY1MTc5ZmNiMTZkMDp7Il9hdXRoX3VzZXJfaGFzaCI6ImZhZjBlODkzZjQzNmEwYjQ5MDM0MWQ4ZTI5NmJhZTljMGE5MWFmZGMiLCJfYXV0aF91c2VyX2JhY2tlbmQiOiJkamFuZ28uY29udHJpYi5hdXRoLmJhY2tlbmRzLk1vZGVsQmFja2VuZCIsIl9hdXRoX3VzZXJfaWQiOiIxIn0="}, "model": "sessions.session", "pk": "g52mjvztpvdg2dtqqv6remp9f4veqpdj"}, {"fields": {"expire_date": "2016-05-16T18:22:44.607Z", "session_data": "ZDc1MTk2MjUwNTEzNWIwYTllOWM1MWQ4MzgxNjAyZGEwYWZkM2RiNzp7ImNtc19sb2dfbGF0ZXN0Ijo5MzMsIl9hdXRoX3VzZXJfaGFzaCI6ImZhZjBlODkzZjQzNmEwYjQ5MDM0MWQ4ZTI5NmJhZTljMGE5MWFmZGMiLCJfYXV0aF91c2VyX2JhY2tlbmQiOiJkamFuZ28uY29udHJpYi5hdXRoLmJhY2tlbmRzLk1vZGVsQmFja2VuZCIsIl9hdXRoX3VzZXJfaWQiOiIxIn0="}, "model": "sessions.session", "pk": "hzlude7eivrmf0v8408pu3xkiz7rt52c"}, {"fields": {"expire_date": "2016-05-23T17:59:23.609Z", "session_data": "ZGQ0ZjExZGUzY2MwNGFlY2M0NzBiYTgxMzM2MDgwZWNkNjhmYzBjODp7ImNtc19sb2dfbGF0ZXN0IjoxMDY1NCwiX2F1dGhfdXNlcl9oYXNoIjoiZmFmMGU4OTNmNDM2YTBiNDkwMzQxZDhlMjk2YmFlOWMwYTkxYWZkYyIsIl9hdXRoX3VzZXJfYmFja2VuZCI6ImRqYW5nby5jb250cmliLmF1dGguYmFja2VuZHMuTW9kZWxCYWNrZW5kIiwiX2F1dGhfdXNlcl9pZCI6IjEifQ=="}, "model": "sessions.session", "pk": "o4fg2qj3rvxwsi4ego0jeok7u1v35vzy"}, {"fields": {"expire_date": "2016-06-14T15:37:48.140Z", "session_data": "ZTQ2ZjRkMDc3YzliZGQ5YzY4NjNhODA5MWY2ZGY1MTc5ZmNiMTZkMDp7Il9hdXRoX3VzZXJfaGFzaCI6ImZhZjBlODkzZjQzNmEwYjQ5MDM0MWQ4ZTI5NmJhZTljMGE5MWFmZGMiLCJfYXV0aF91c2VyX2JhY2tlbmQiOiJkamFuZ28uY29udHJpYi5hdXRoLmJhY2tlbmRzLk1vZGVsQmFja2VuZCIsIl9hdXRoX3VzZXJfaWQiOiIxIn0="}, "model": "sessions.session", "pk": "xz7v7zg7jch2m8fap7lqpciwva3xq0dp"}, {"fields": {"expire_date": "2016-05-30T17:33:40.798Z", "session_data": "NDA0NTYyNWUxMjgwZTU2ZTc0NDhlYzBjOGU0N2M2OTFjNjYxODdjYjp7ImNtc19sb2dfbGF0ZXN0IjoxMDY5MiwiX2F1dGhfdXNlcl9oYXNoIjoiZmFmMGU4OTNmNDM2YTBiNDkwMzQxZDhlMjk2YmFlOWMwYTkxYWZkYyIsIl9hdXRoX3VzZXJfaWQiOiIxIiwiX2F1dGhfdXNlcl9iYWNrZW5kIjoiZGphbmdvLmNvbnRyaWIuYXV0aC5iYWNrZW5kcy5Nb2RlbEJhY2tlbmQifQ=="}, "model": "sessions.session", "pk": "zbfh49iexopuee2evfdh5pm8nhqdn7ec"}, {"fields": {"sigla": "DACOM", "nome": "Departamento Acad\u00eamico de Computa\u00e7\u00e3o"}, "model": "desenvolvimento.departamentoacademico", "pk": 1}, {"fields": {"sigla": "DAHUM", "nome": "Departamento Acad\u00eamico de Humanas"}, "model": "desenvolvimento.departamentoacademico", "pk": 2}